mcp_modules_pkg/__init__.py
mcp_modules_pkg/db_connector/__init__.py
mcp_modules_pkg/db_connector/base.py
mcp_modules_pkg/db_connector/connection.py
mcp_modules_pkg/db_connector/database.py
mcp_modules_pkg/db_connector/mysql.py
mcp_modules_pkg/db_connector/postgre.py
mcp_modules_pkg/mcp_modules/__init__.py
mcp_modules_pkg/mcp_modules/base_invoker.py
mcp_modules_pkg/mcp_modules/mcp_logger.py
mcp_modules_pkg-0.1.15.dist-info/METADATA
mcp_modules_pkg-0.1.15.dist-info/WHEEL
mcp_modules_pkg-0.1.15.dist-info/top_level.txt
mcp_modules_pkg-0.1.15.dist-info/RECORD
