Metadata-Version: 2.4
Name: mcp-modules-pkg
Version: 0.1.15
Summary: 통합된 DB connector, MCP 모듈(base invoker, mcp loggers) 패키지
Author-email: yepark <yepark@bitmango.com>
License: MIT
Keywords: database,mcp-logger,mcp-invoker
Classifier: Programming Language :: Python :: 3
Requires-Python: >=3.11
Requires-Dist: pandas
Requires-Dist: psycopg2-binary
Requires-Dist: sqlalchemy
Requires-Dist: cryptography
